kpnapistore/__init__.py
kpnapistore/base.py
kpnapistore/exceptions.py
kpnapistore/messaging/__init__.py
kpnapistore/messaging/sms_kpn/__init__.py
kpnapistore/messaging/sms_kpn/v1/__init__.py
tests/__init__.py
tests/test_kpnapiclient.py
kpn_api_store-0.0.1.dist-info/COPYING
kpn_api_store-0.0.1.dist-info/COPYING.LESSER
kpn_api_store-0.0.1.dist-info/METADATA
kpn_api_store-0.0.1.dist-info/WHEEL
kpn_api_store-0.0.1.dist-info/top_level.txt
kpn_api_store-0.0.1.dist-info/RECORD
