Metadata-Version: 2.1
Name: kpn-api-store
Version: 0.0.1
Summary: Client library for APIs provided by the KPN API Store
Home-page: https://github.com/roaldnefs/kpn-api-store-python
Author: Roald Nefs
Author-email: info@roaldnefs.com
License: LGPLv3
Platform: UNKNOWN
Classifier: Development Status :: 1 - Planning
Classifier: Intended Audience :: Developers
Classifier: Intended Audience :: System Administrators
Classifier: License :: OSI Approved :: GNU Lesser General Public License v3 (LGPLv3)
Classifier: Programming Language :: Python
Classifier: Programming Language :: Python :: 3
Classifier: Programming Language :: Python :: 3.6
Classifier: Programming Language :: Python :: 3.7
Classifier: Programming Language :: Python :: 3.8
Classifier: Programming Language :: Python :: 3.9
Requires-Python: >=3.6.12
Requires-Dist: requests (>=2.25.1)
